django_upthor-0.9.1.dist-info/DESCRIPTION.rst
django_upthor-0.9.1.dist-info/METADATA
django_upthor-0.9.1.dist-info/RECORD
django_upthor-0.9.1.dist-info/WHEEL
django_upthor-0.9.1.dist-info/metadata.json
django_upthor-0.9.1.dist-info/top_level.txt
upthor/__init__.py
upthor/admin.py
upthor/cron.py
upthor/fields.py
upthor/forms.py
upthor/models.py
upthor/tests.py
upthor/urls.py
upthor/views.py
upthor/widgets.py
upthor/management/__init__.py
upthor/management/commands/__init__.py
upthor/management/commands/clean_temporary_files.py
upthor/migrations/0001_initial.py
upthor/migrations/__init__.py
upthor/static/upthor/css/font-awesome.css
upthor/static/upthor/css/main.css
upthor/static/upthor/fonts/FontAwesome.otf
upthor/static/upthor/fonts/fontawesome-webfont.eot
upthor/static/upthor/fonts/fontawesome-webfont.svg
upthor/static/upthor/fonts/fontawesome-webfont.ttf
upthor/static/upthor/fonts/fontawesome-webfont.woff
upthor/static/upthor/js/jquery.fileupload.js
upthor/static/upthor/js/jquery.iframe-transport.js
upthor/static/upthor/js/jquery.ui.widget.js
upthor/static/upthor/js/upthor-fileupload.js
