Metadata-Version: 2.0
Name: django-upthor
Version: 0.9.1
Summary: django-upthor provides a django application for simple ajax file uploads.
Home-page: https://github.com/thorgate/django-upthor
Author: Thorgate
Author-email: info@thorgate.eu
License: UNKNOWN
Platform: UNKNOWN
Classifier: Development Status :: 4 - Beta
Classifier: Environment :: Web Environment
Classifier: Framework :: Django
Classifier: Intended Audience :: Developers
Classifier: License :: OSI Approved :: BSD License
Classifier: Operating System :: OS Independent
Classifier: Programming Language :: Python
Classifier: Programming Language :: Python :: 2
Classifier: Programming Language :: Python :: 3
Requires-Dist: Django
Requires-Dist: Pillow
